fuel_efficency/__init__.py
fuel_efficency/algorithms/__init__.py
fuel_efficency/algorithms/a_star.py
fuel_efficency/algorithms/context.py
fuel_efficency/algorithms/dijkstra.py
fuel_efficency/algorithms/path_finding.py
fuel_efficency/entities/__init__.py
fuel_efficency/entities/down_hill.py
fuel_efficency/entities/node.py
fuel_efficency/entities/plateau.py
fuel_efficency/entities/position.py
fuel_efficency/entities/up_hill.py
fuel_efficency/entities/valley.py
fuel_efficiency_joeljunior95-0.0.3.dist-info/METADATA
fuel_efficiency_joeljunior95-0.0.3.dist-info/WHEEL
fuel_efficiency_joeljunior95-0.0.3.dist-info/top_level.txt
fuel_efficiency_joeljunior95-0.0.3.dist-info/RECORD
