Metadata-Version: 2.1
Name: fuel_efficiency_joeljunior95
Version: 0.0.3
Summary: Fuel efficiency based on distance and terrain type.
Author-email: Joel Souza <joel.junior.95@gmail.com>
Project-URL: Homepage, https://github.com/joeljunior95/fuel_efficiency
Project-URL: Issues, https://github.com/joeljunior95/fuel_efficiency/issues
Classifier: Programming Language :: Python :: 3
Classifier: License :: OSI Approved :: MIT License
Classifier: Operating System :: OS Independent
Requires-Python: >=3.10.4
